lib_pod5/__init__.py
lib_pod5/_version.py
lib_pod5/pod5_format_pybind.cpython-314-aarch64-linux-gnu.so
lib_pod5/pod5_format_pybind.pyi
lib_pod5/py.typed
lib_pod5-0.3.35.dist-info/METADATA
lib_pod5-0.3.35.dist-info/WHEEL
lib_pod5-0.3.35.dist-info/top_level.txt
lib_pod5-0.3.35.dist-info/RECORD
