Metadata-Version: 2.4
Name: lib_pod5
Version: 0.3.35
Summary: Python bindings for the POD5 file format
Author-email: Oxford Nanopore Technologies plc <support@nanoporetech.com>
Project-URL: Homepage, https://github.com/nanoporetech/pod5-file-format
Project-URL: Issues, https://github.com/nanoporetech/pod5-file-format/issues
Project-URL: Documentation, https://pod5-file-format.readthedocs.io/en/latest/
Keywords: nanopore
Classifier: Environment :: Console
Classifier: Intended Audience :: Developers
Classifier: Intended Audience :: Science/Research
Classifier: License :: OSI Approved :: Mozilla Public License 2.0 (MPL 2.0)
Classifier: Natural Language :: English
Classifier: Programming Language :: Python :: 3
Classifier: Topic :: Scientific/Engineering :: Bio-Informatics
Requires-Python: ~=3.8
Requires-Dist: numpy>=1.21.0
Provides-Extra: dev
Requires-Dist: build; extra == "dev"
Requires-Dist: pytest~=7.3; extra == "dev"
